{"cameraMode":{"drawMode":0,"name":"Shaded","section":"Shading Mode"},"sceneLighting":true,"audioPlay":false,"sceneViewState":{"m_AlwaysRefresh":false,"showFog":true,"showSkybox":true,"showFlares":true,"showImageEffects":true,"showParticleSystems":true,"showVisualEffectGraphs":true,"m_FxEnabled":true},"in2DMode":false,"pivot":{"x":-5.498723983764648,"y":1.8029890060424805,"z":-2.297292947769165},"rotation":{"x":0.10012165457010269,"y":0.14780576527118684,"z":-0.01504608616232872,"w":0.9839019775390625},"size":5.868001937866211,"orthographic":false}